kalouk/__init__.py
kalouk/dataset.py
kalouk-0.1.0.dist-info/METADATA
kalouk-0.1.0.dist-info/WHEEL
kalouk-0.1.0.dist-info/entry_points.txt
kalouk-0.1.0.dist-info/licenses/LICENSE
kalouk-0.1.0.dist-info/RECORD
