Metadata-Version: 2.4
Name: kalouk
Version: 0.1.0
Summary: A Python package for creating dataset metadata using Schema.org's Dataset type and sending it to Kalouk's API
Author-email: Fabián Abarca <fabian.abarca@ucr.ac.cr>
License-File: LICENSE
Requires-Python: >=3.12
Requires-Dist: requests>=2.32.4
